LICENSE
py3a/__init__.py
py3a/py3a/__init__.py
py3a/py3a/enums.py
py3a/py3a/errors.py
py3a/py3a/lib.py
py3a/pyproject.toml
py3a/tests/__init__.py
py3a/tests/test_art.py
py3a/tests/test_body.py
py3a/tests/test_enums.py
py3a/tests/test_header.py
py3a/tests/test_py3a.py
py3a-1.0.0.dist-info/LICENSE
py3a-1.0.0.dist-info/WHEEL
py3a-1.0.0.dist-info/METADATA
py3a-1.0.0.dist-info/RECORD
