Metadata-Version: 2.1
Name: py3a
Version: 1.0.0
Summary: Lib for reading and writing 3a format
Home-page: https://github.com/DomesticMoth/py3a
License: GPLv3
Author: DomesticMoth
Requires-Python: >=3.7,<4.0
Classifier: Environment :: Console
Classifier: License :: OSI Approved :: GNU General Public License v3 (GPLv3)
Classifier: License :: Other/Proprietary License
Classifier: Programming Language :: Python :: 3
Classifier: Programming Language :: Python :: 3.7
Classifier: Programming Language :: Python :: 3.8
Classifier: Programming Language :: Python :: 3.9
Project-URL: Repository, https://github.com/DomesticMoth/py3a
